README.md
pyproject.toml
xlnstorch/__init__.py
xlnstorch/_build_ext.py
xlnstorch/autograd.py
xlnstorch/convert_model.py
xlnstorch/dispatch_table.py
xlnstorch/sbdb_dispatch_table.py
xlnstorch/tensor.py
xlnstorch/tensor_utils.py
xlnstorch/transforms.py
xlnstorch.egg-info/PKG-INFO
xlnstorch.egg-info/SOURCES.txt
xlnstorch.egg-info/dependency_links.txt
xlnstorch.egg-info/requires.txt
xlnstorch.egg-info/top_level.txt
xlnstorch/benchmark/__init__.py
xlnstorch/benchmark/core.py
xlnstorch/benchmark/operator_bench.py
xlnstorch/csrc/__init__.py
xlnstorch/csrc/lns_addition.cpp
xlnstorch/csrc/lns_addition.h
xlnstorch/csrc/lns_constants.h
xlnstorch/csrc/lns_convolution.cpp
xlnstorch/csrc/lns_convolution.h
xlnstorch/csrc/lns_matmul.cpp
xlnstorch/csrc/lns_matmul.h
xlnstorch/csrc/lns_multiplication.cpp
xlnstorch/csrc/lns_multiplication.h
xlnstorch/csrc/lns_pooling.cpp
xlnstorch/csrc/lns_pooling.h
xlnstorch/csrc/lns_utils.cpp
xlnstorch/csrc/lns_utils.h
xlnstorch/csrc/main.cpp
xlnstorch/csrc/pointwise_ops.cpp
xlnstorch/csrc/pointwise_ops.h
xlnstorch/csrc/sbdb.cpp
xlnstorch/csrc/sbdb.h
xlnstorch/csrc/vectorized_ops.cpp
xlnstorch/csrc/vectorized_ops.h
xlnstorch/nn/__init__.py
xlnstorch/nn/_layer.py
xlnstorch/nn/convolutional_layers.py
xlnstorch/nn/dropout_layers.py
xlnstorch/nn/init.py
xlnstorch/nn/linear_layers.py
xlnstorch/nn/normalization_layers.py
xlnstorch/nn/pooling_layers.py
xlnstorch/nn/recurrent_layers.py
xlnstorch/nn/transformer_layers.py
xlnstorch/operators/__init__.py
xlnstorch/operators/activation_ops.py
xlnstorch/operators/addition_ops.py
xlnstorch/operators/arithmetic_ops.py
xlnstorch/operators/comparison_ops.py
xlnstorch/operators/internal_lns_ops.py
xlnstorch/operators/layer_ops.py
xlnstorch/operators/loss_ops.py
xlnstorch/operators/misc_ops.py
xlnstorch/operators/unary_ops.py
xlnstorch/operators/_C/__init__.py
xlnstorch/operators/_C/addition_ops.py
xlnstorch/operators/_C/convolution_ops.py
xlnstorch/operators/_C/pooling_ops.py
xlnstorch/operators/implementations/__init__.py
xlnstorch/operators/implementations/tab.py
xlnstorch/operators/implementations/utah_tayco.py
xlnstorch/optim/__init__.py
xlnstorch/optim/_optimizer.py
