Metadata-Version: 2.4
Name: xlnstorch
Version: 1.0.0
Summary: A PyTorch backend for LNS experimentation
Requires-Python: >=3.8
Requires-Dist: torch>=2.0
Requires-Dist: xlns
Requires-Dist: numpy
